{"state":{"passed":2,"failed":0,"skipped":0},"start":"2017-11-25T02:45:21.504Z","end":"2017-11-25T02:45:34.085Z","capabilities":{"maxInstances":5,"browserName":"firefox"},"host":"77.87.16.39","port":8088,"baseUrl":"http://arduino.vn/","framework":"mocha","mochaOpts":{"timeout":10000,"ui":"bdd"},"suites":[{"name":"my awesome website","duration":0,"start":"2017-11-25T02:45:29.460Z","tests":[],"hooks":[]},{"name":"my awesome website","duration":4417,"start":"2017-11-25T02:45:29.461Z","end":"2017-11-25T02:45:33.878Z","tests":[{"name":"should do some chai assertions","start":"2017-11-25T02:45:29.461Z","end":"2017-11-25T02:45:33.877Z","duration":4416,"state":"pass"}],"hooks":[{"start":"2017-11-25T02:45:29.462Z","end":"2017-11-25T02:45:29.462Z","duration":0,"title":"\"before each\" hook","associatedSuite":"my awesome website","associatedTest":"should do some chai assertions"},{"start":"2017-11-25T02:45:33.877Z","end":"2017-11-25T02:45:33.877Z","duration":0,"title":"\"after each\" hook","associatedSuite":"my awesome website","associatedTest":"should do some chai assertions"},{"start":"2017-11-25T02:45:33.878Z","end":"2017-11-25T02:45:33.879Z","duration":1,"title":"\"after all\" hook","associatedSuite":"my awesome website"}]},{"name":"my awesome website","duration":0,"start":"2017-11-25T02:45:26.238Z","tests":[],"hooks":[]},{"name":"my awesome website","duration":4161,"start":"2017-11-25T02:45:26.239Z","end":"2017-11-25T02:45:30.400Z","tests":[{"name":"should do some chai assertions","start":"2017-11-25T02:45:26.240Z","end":"2017-11-25T02:45:30.400Z","duration":4160,"state":"pass"}],"hooks":[{"start":"2017-11-25T02:45:26.241Z","end":"2017-11-25T02:45:26.241Z","duration":0,"title":"\"before each\" hook","associatedSuite":"my awesome website","associatedTest":"should do some chai assertions"},{"start":"2017-11-25T02:45:30.400Z","end":"2017-11-25T02:45:30.400Z","duration":0,"title":"\"after each\" hook","associatedSuite":"my awesome website","associatedTest":"should do some chai assertions"},{"start":"2017-11-25T02:45:30.400Z","end":"2017-11-25T02:45:30.401Z","duration":1,"title":"\"after all\" hook","associatedSuite":"my awesome website"}]}]}